lpb_lib/__init__.py
lpb_lib/ai.py
lpb_lib/big_query.py
lpb_lib/compute_log.py
lpb_lib/gdrive.py
lpb_lib/geo.py
lpb_lib/get_env.py
lpb_lib/gmail.py
lpb_lib/gsheet.py
lpb_lib/main.py
lpb_lib/slack.py
lpb_lib-1.dist-info/LICENSE
lpb_lib-1.dist-info/METADATA
lpb_lib-1.dist-info/WHEEL
lpb_lib-1.dist-info/top_level.txt
lpb_lib-1.dist-info/RECORD
