Metadata-Version: 2.1
Name: lpb_lib
Version: 1
Summary: This package contains tools that will help me to develop my projects
Home-page: https://github.com/Fajitas08090/lpb_lib
Author: Maxime Renac
Author-email: maxime.renac@lepetitballon.com
Classifier: Programming Language :: Python :: 3
Classifier: License :: OSI Approved :: MIT License
Classifier: Operating System :: OS Independent
Requires-Python: >=3.10
License-File: LICENSE
